animation/__init__.py
animation/animation.py
animation/static/css/animation.css
animation/static/css/jquery.ui.labeledslider.css
animation/static/html/animation.html
animation/static/images/Pin_tumbler_bad_key.svg
animation/static/images/Pin_tumbler_no_key.svg
animation/static/images/Pin_tumbler_unlocked.svg
animation/static/images/Pin_tumbler_with_key.svg
animation/static/js/src/animation.js
animation/static/js/src/jquery.ui.labeledslider.js
animation_xblock-0.2.0.dist-info/LICENSE
animation_xblock-0.2.0.dist-info/METADATA
animation_xblock-0.2.0.dist-info/WHEEL
animation_xblock-0.2.0.dist-info/entry_points.txt
animation_xblock-0.2.0.dist-info/top_level.txt
animation_xblock-0.2.0.dist-info/RECORD
