Metadata-Version: 2.1
Name: animation-xblock
Version: 0.2.0
Summary: animation XBlock
Home-page: UNKNOWN
License: UNKNOWN
Platform: UNKNOWN
License-File: LICENSE
Requires-Dist: XBlock
